lux/__init__.py
lux/__main__.py
lux/cli.py
lux/binary/__init__.py
lux/binary/constants.py
lux/binary/decoder.py
lux/binary/encoder.py
lux/core/adaptive.py
lux/core/analyzer.py
lux/core/constants.py
lux/core/decoder.py
lux/core/encoder.py
lux/core/exceptions.py
lux/core/stream.py
lux/core/types.py
lux/core/utils.py
lux/integrations/__init__.py
lux/integrations/ai_sdk.py
lux/integrations/langchain.py
lux/integrations/openai.py
lux/llm/llm_client.py
lux/llm/optimizer.py
lux/llm/splitter.py
lux/llm/token_counter.py
lux/schema/inference.py
lux/schema/schema.py
lux/tools/__init__.py
lux/tools/helpers.py
lux/tools/printer.py
lux/tools/validator.py
lux/versioning/__init__.py
lux/versioning/migration.py
lux/versioning/versioning.py
lux_format-1.2.1.dist-info/METADATA
lux_format-1.2.1.dist-info/WHEEL
lux_format-1.2.1.dist-info/entry_points.txt
lux_format-1.2.1.dist-info/top_level.txt
lux_format-1.2.1.dist-info/RECORD
