Metadata-Version: 2.4
Name: lux-format
Version: 1.2.1
Summary: Lightweight Ultra-compressed Xchange v1.2.1 - Human-readable data format with 30%+ compression over JSON, now with adaptive encoding
Author-email: TonyX <hi@tonyx.dev>
Maintainer-email: TonyX <hi@tonyx.dev>
License: MIT
Project-URL: Homepage, https://lux.tonyx.dev
Project-URL: Documentation, https://github.com/mrtinhnguyen/LUX/blob/main/README.md
Project-URL: Repository, https://github.com/mrtinhnguyen/LUX
Project-URL: Issues, https://github.com/mrtinhnguyen/LUX/issues
Keywords: lux,serialization,llm,compression,token-efficiency,data-format,json-alternative,toon,token-efficient
Classifier: Development Status :: 5 - Production/Stable
Classifier: Intended Audience :: Developers
Classifier: Topic :: Software Development :: Libraries :: Python Modules
Classifier: Topic :: Text Processing :: Markup
Classifier: Programming Language :: Python :: 3
Classifier: Programming Language :: Python :: 3.8
Classifier: Programming Language :: Python :: 3.9
Classifier: Programming Language :: Python :: 3.10
Classifier: Programming Language :: Python :: 3.11
Classifier: Programming Language :: Python :: 3.12
Classifier: Operating System :: OS Independent
Requires-Python: >=3.8
